si_utils/__init__.py
si_utils/_vendor/__init__.py
si_utils/_vendor/appdirs.LICENSE.txt
si_utils/_vendor/appdirs.py
si_utils/_vendor/boltons/LICENSE
si_utils/_vendor/boltons/__init__.py
si_utils/_vendor/boltons/cacheutils.py
si_utils/_vendor/boltons/debugutils.py
si_utils/_vendor/boltons/deprutils.py
si_utils/_vendor/boltons/dictutils.py
si_utils/_vendor/boltons/easterutils.py
si_utils/_vendor/boltons/ecoutils.py
si_utils/_vendor/boltons/excutils.py
si_utils/_vendor/boltons/fileutils.py
si_utils/_vendor/boltons/formatutils.py
si_utils/_vendor/boltons/funcutils.py
si_utils/_vendor/boltons/gcutils.py
si_utils/_vendor/boltons/ioutils.py
si_utils/_vendor/boltons/iterutils.py
si_utils/_vendor/boltons/jsonutils.py
si_utils/_vendor/boltons/listutils.py
si_utils/_vendor/boltons/mathutils.py
si_utils/_vendor/boltons/mboxutils.py
si_utils/_vendor/boltons/namedutils.py
si_utils/_vendor/boltons/pathutils.py
si_utils/_vendor/boltons/queueutils.py
si_utils/_vendor/boltons/setutils.py
si_utils/_vendor/boltons/socketutils.py
si_utils/_vendor/boltons/statsutils.py
si_utils/_vendor/boltons/strutils.py
si_utils/_vendor/boltons/tableutils.py
si_utils/_vendor/boltons/tbutils.py
si_utils/_vendor/boltons/timeutils.py
si_utils/_vendor/boltons/typeutils.py
si_utils/_vendor/boltons/urlutils.py
si_utils/_vendor/decorator.LICENSE.txt
si_utils/_vendor/decorator.py
si_utils/_vendor/toml/LICENSE
si_utils/_vendor/toml/__init__.py
si_utils/_vendor/toml/decoder.py
si_utils/_vendor/toml/encoder.py
si_utils/_vendor/toml/ordered.py
si_utils/_vendor/toml/tz.py
si_utils/dev_utils.py
si_utils/log.py
si_utils/main.py
si_utils/nested_data.py
si_utils/py.typed
si_utils/yaml.py
si_utils-0.4.3.dist-info/LICENSE
si_utils-0.4.3.dist-info/WHEEL
si_utils-0.4.3.dist-info/METADATA
si_utils-0.4.3.dist-info/RECORD
