Metadata-Version: 2.1
Name: si-utils
Version: 0.4.3
Summary: an opinionated set of utilities designed to be easily included in any number of projects
License: MIT
Author: Alex Tremblay
Author-email: alex.tremblay@utoronto.ca
Requires-Python: >=3.6,<4.0
Classifier: License :: OSI Approved :: MIT License
Classifier: Programming Language :: Python :: 3
Classifier: Programming Language :: Python :: 3.6
Classifier: Programming Language :: Python :: 3.7
Classifier: Programming Language :: Python :: 3.8
Classifier: Programming Language :: Python :: 3.9
Provides-Extra: dev-utils
Provides-Extra: sentry
Provides-Extra: yaml
Requires-Dist: deepmerge; extra == "yaml"
Requires-Dist: jinja2
Requires-Dist: loguru
Requires-Dist: pydantic; extra == "yaml"
Requires-Dist: ruamel.yaml; extra == "yaml"
Requires-Dist: semver; extra == "dev-utils"
Requires-Dist: sentry-sdk; extra == "sentry"
Requires-Dist: tomlkit; extra == "dev-utils"
